rscripts_api/__init__.py
rscripts_api/client.py
rscripts_api-1.0.1.dist-info/METADATA
rscripts_api-1.0.1.dist-info/WHEEL
rscripts_api-1.0.1.dist-info/top_level.txt
rscripts_api-1.0.1.dist-info/RECORD
