Metadata-Version: 2.1
Name: rscripts-api
Version: 1.0.1
Summary: A Python wrapper for the Rscripts.net API
Author: Flames aka Aura
Classifier: Programming Language :: Python :: 3
Classifier: Operating System :: OS Independent
Requires-Python: >=3.6
Requires-Dist: requests
